{
  "batch_label": "8V3_LONG100_REVIEWED",
  "strategy_name": "8V3_L09_V25_compression_release",
  "side": "long",
  "description": "beartrap compression release",
  "timeframe": "5m",
  "processed_symbols": 597,
  "trades": 2608,
  "wins": 837,
  "losses": 1771,
  "win_rate_pct": 32.09355828220859,
  "final_return_pct": -2.8358316151178453,
  "max_return_pct": 2.6471867124176374,
  "max_drawdown_pct": 5.4763344422724565,
  "cd_value": 91.84313356607325,
  "baseline_cd_value": 121.53,
  "ruined": false,
  "verdict": "mdd_fail"
}