[
  {
    "experiment_group": "json_only_short_strict",
    "experiment": "rrcore_baseline",
    "strategy": "overextension_reversion_v1_json_only_timeout18_time_reduce_v36_rr_core_exploration_rrcore_baseline",
    "symbols": NaN,
    "trades": 87120.0,
    "final_asset": 1459.0129390528086,
    "final_return_pct": 1359.0129390528086,
    "peak_asset": 1459.9276694697303,
    "peak_growth_pct": 1359.9276694697303,
    "win_rate_pct": 29.547750229568408,
    "pf": 1.2761747324126367,
    "mdd_pct": -38.76976677941407,
    "max_conc": 386.0,
    "position_fraction": 0.01,
    "fee_per_side": 0.0004,
    "summary_path": "results_json_only_timeout18_time_reduce_v36_rr_core_exploration/rrcore_baseline/summary.json",
    "delta_final_return_pct": 0.0,
    "delta_pf": 0.0,
    "delta_mdd_pct": 0.0,
    "delta_max_conc": 0.0,
    "return_retention_pct": 100.0,
    "mdd_improved": false,
    "pf_improved": false,
    "conc_reduced": false,
    "verdict": "baseline"
  },
  {
    "experiment_group": "json_only_short_strict",
    "experiment": "rrcore_rr30",
    "strategy": "overextension_reversion_v1_json_only_timeout18_time_reduce_v36_rr_core_exploration_rrcore_rr30",
    "symbols": NaN,
    "trades": 87100.0,
    "final_asset": 1914.1920712307528,
    "final_return_pct": 1814.1920712307528,
    "peak_asset": 1915.5170120408964,
    "peak_growth_pct": 1815.5170120408964,
    "win_rate_pct": 28.7841561423651,
    "pf": 1.3136522044705916,
    "mdd_pct": -36.079566047193346,
    "max_conc": 387.0,
    "position_fraction": 0.01,
    "fee_per_side": 0.0004,
    "summary_path": "results_json_only_timeout18_time_reduce_v36_rr_core_exploration/rrcore_rr30/summary.json",
    "delta_final_return_pct": 455.1791321779442,
    "delta_pf": 0.03747747205795493,
    "delta_mdd_pct": 2.690200732220724,
    "delta_max_conc": 1.0,
    "return_retention_pct": 133.49336265298476,
    "mdd_improved": true,
    "pf_improved": true,
    "conc_reduced": false,
    "verdict": "hold"
  },
  {
    "experiment_group": "json_only_short_strict",
    "experiment": "rrcore_timeout40_rr30",
    "strategy": "overextension_reversion_v1_json_only_timeout18_time_reduce_v36_rr_core_exploration_rrcore_timeout40_rr30",
    "symbols": NaN,
    "trades": 87086.0,
    "final_asset": 2140.32885949097,
    "final_return_pct": 2040.32885949097,
    "peak_asset": 2141.762596786411,
    "peak_growth_pct": 2041.7625967864112,
    "win_rate_pct": 25.432331258755713,
    "pf": 1.3152661713093794,
    "mdd_pct": -36.62568781412456,
    "max_conc": 387.0,
    "position_fraction": 0.01,
    "fee_per_side": 0.0004,
    "summary_path": "results_json_only_timeout18_time_reduce_v36_rr_core_exploration/rrcore_timeout40_rr30/summary.json",
    "delta_final_return_pct": 681.3159204381614,
    "delta_pf": 0.039091438896742714,
    "delta_mdd_pct": 2.144078965289509,
    "delta_max_conc": 1.0,
    "return_retention_pct": 150.13314449478443,
    "mdd_improved": true,
    "pf_improved": true,
    "conc_reduced": false,
    "verdict": "hold"
  },
  {
    "experiment_group": "json_only_short_strict",
    "experiment": "rrcore_asym_both_balanced",
    "strategy": "overextension_reversion_v1_json_only_timeout18_time_reduce_v36_rr_core_exploration_rrcore_asym_both_balanced",
    "symbols": NaN,
    "trades": 67100.0,
    "final_asset": 1145.4003753309182,
    "final_return_pct": 1045.4003753309182,
    "peak_asset": 1146.1184858663523,
    "peak_growth_pct": 1046.1184858663523,
    "win_rate_pct": 29.998509687034275,
    "pf": 1.3180656206889731,
    "mdd_pct": -37.722644208447406,
    "max_conc": 379.0,
    "position_fraction": 0.01,
    "fee_per_side": 0.0004,
    "summary_path": "results_json_only_timeout18_time_reduce_v36_rr_core_exploration/rrcore_asym_both_balanced/summary.json",
    "delta_final_return_pct": -313.6125637218904,
    "delta_pf": 0.04189088827633647,
    "delta_mdd_pct": 1.047122570966664,
    "delta_max_conc": -7.0,
    "return_retention_pct": 76.92350420589307,
    "mdd_improved": true,
    "pf_improved": true,
    "conc_reduced": true,
    "verdict": "hold"
  },
  {
    "experiment_group": "json_only_short_strict",
    "experiment": "rrcore_timeout18",
    "strategy": "overextension_reversion_v1_json_only_timeout18_time_reduce_v36_rr_core_exploration_rrcore_timeout18",
    "symbols": NaN,
    "trades": 87155.0,
    "final_asset": 1417.8712428841097,
    "final_return_pct": 1317.8712428841097,
    "peak_asset": 1418.303682651846,
    "peak_growth_pct": 1318.303682651846,
    "win_rate_pct": 33.58958177958809,
    "pf": 1.2682567627496986,
    "mdd_pct": -37.97098171413242,
    "max_conc": 386.0,
    "position_fraction": 0.01,
    "fee_per_side": 0.0004,
    "summary_path": "results_json_only_timeout18_time_reduce_v36_rr_core_exploration/rrcore_timeout18/summary.json",
    "delta_final_return_pct": -41.1416961686989,
    "delta_pf": -0.007917969662938118,
    "delta_mdd_pct": 0.798785065281649,
    "delta_max_conc": 0.0,
    "return_retention_pct": 96.97267811170559,
    "mdd_improved": true,
    "pf_improved": false,
    "conc_reduced": false,
    "verdict": "hold"
  },
  {
    "experiment_group": "json_only_short_strict",
    "experiment": "rrcore_timeout18_rr15",
    "strategy": "overextension_reversion_v1_json_only_timeout18_time_reduce_v36_rr_core_exploration_rrcore_timeout18_rr15",
    "symbols": NaN,
    "trades": 87220.0,
    "final_asset": 844.3194132539018,
    "final_return_pct": 744.3194132539018,
    "peak_asset": 844.5769241476413,
    "peak_growth_pct": 744.5769241476412,
    "win_rate_pct": 36.196973171290985,
    "pf": 1.2129006562998208,
    "mdd_pct": -37.739170570122624,
    "max_conc": 386.0,
    "position_fraction": 0.01,
    "fee_per_side": 0.0004,
    "summary_path": "results_json_only_timeout18_time_reduce_v36_rr_core_exploration/rrcore_timeout18_rr15/summary.json",
    "delta_final_return_pct": -614.6935257989069,
    "delta_pf": -0.06327407611281588,
    "delta_mdd_pct": 1.0305962092914456,
    "delta_max_conc": 0.0,
    "return_retention_pct": 54.76911895869587,
    "mdd_improved": true,
    "pf_improved": false,
    "conc_reduced": false,
    "verdict": "fail"
  },
  {
    "experiment_group": "json_only_short_strict",
    "experiment": "rrcore_rr15",
    "strategy": "overextension_reversion_v1_json_only_timeout18_time_reduce_v36_rr_core_exploration_rrcore_rr15",
    "symbols": NaN,
    "trades": 87196.0,
    "final_asset": 834.2477692796574,
    "final_return_pct": 734.2477692796574,
    "peak_asset": 834.7708022078674,
    "peak_growth_pct": 734.7708022078674,
    "win_rate_pct": 33.470572044589204,
    "pf": 1.2152387080732785,
    "mdd_pct": -38.39268033158096,
    "max_conc": 386.0,
    "position_fraction": 0.01,
    "fee_per_side": 0.0004,
    "summary_path": "results_json_only_timeout18_time_reduce_v36_rr_core_exploration/rrcore_rr15/summary.json",
    "delta_final_return_pct": -624.7651697731512,
    "delta_pf": -0.060936024339358186,
    "delta_mdd_pct": 0.37708644783310774,
    "delta_max_conc": 0.0,
    "return_retention_pct": 54.028019026176906,
    "mdd_improved": true,
    "pf_improved": false,
    "conc_reduced": false,
    "verdict": "fail"
  },
  {
    "experiment_group": "json_only_short_strict",
    "experiment": "rrcore_no_failfast",
    "strategy": "overextension_reversion_v1_json_only_timeout18_time_reduce_v36_rr_core_exploration_rrcore_no_failfast",
    "symbols": NaN,
    "trades": 87116.0,
    "final_asset": 1458.7605609728998,
    "final_return_pct": 1358.7605609728998,
    "peak_asset": 1459.6751331609942,
    "peak_growth_pct": 1359.6751331609942,
    "win_rate_pct": 29.551402727397953,
    "pf": 1.2761578273045664,
    "mdd_pct": -38.785541799438015,
    "max_conc": 386.0,
    "position_fraction": 0.01,
    "fee_per_side": 0.0004,
    "summary_path": "results_json_only_timeout18_time_reduce_v36_rr_core_exploration/rrcore_no_failfast/summary.json",
    "delta_final_return_pct": -0.25237807990879446,
    "delta_pf": -1.6905108070286445e-05,
    "delta_mdd_pct": -0.01577502002394482,
    "delta_max_conc": 0.0,
    "return_retention_pct": 99.98142931000461,
    "mdd_improved": false,
    "pf_improved": false,
    "conc_reduced": false,
    "verdict": "fail"
  },
  {
    "experiment_group": "json_only_short_strict",
    "experiment": "rrcore_asym_short_s22",
    "strategy": "overextension_reversion_v1_json_only_timeout18_time_reduce_v36_rr_core_exploration_rrcore_asym_short_s22",
    "symbols": NaN,
    "trades": 78631.0,
    "final_asset": 1312.6496051925924,
    "final_return_pct": 1212.6496051925924,
    "peak_asset": 1313.4725728911578,
    "peak_growth_pct": 1213.4725728911578,
    "win_rate_pct": 29.717287075072175,
    "pf": 1.2941901910258493,
    "mdd_pct": -38.83986531305942,
    "max_conc": 386.0,
    "position_fraction": 0.01,
    "fee_per_side": 0.0004,
    "summary_path": "results_json_only_timeout18_time_reduce_v36_rr_core_exploration/rrcore_asym_short_s22/summary.json",
    "delta_final_return_pct": -146.36333386021624,
    "delta_pf": 0.01801545861321263,
    "delta_mdd_pct": -0.0700985336453499,
    "delta_max_conc": 0.0,
    "return_retention_pct": 89.23017363158976,
    "mdd_improved": false,
    "pf_improved": true,
    "conc_reduced": false,
    "verdict": "fail"
  },
  {
    "experiment_group": "json_only_short_strict",
    "experiment": "rrcore_timeout40",
    "strategy": "overextension_reversion_v1_json_only_timeout18_time_reduce_v36_rr_core_exploration_rrcore_timeout40",
    "symbols": NaN,
    "trades": 87113.0,
    "final_asset": 1502.8664328425366,
    "final_return_pct": 1402.8664328425366,
    "peak_asset": 1503.8086572751617,
    "peak_growth_pct": 1403.8086572751617,
    "win_rate_pct": 26.729649994834297,
    "pf": 1.2711178055057297,
    "mdd_pct": -38.94582794536044,
    "max_conc": 386.0,
    "position_fraction": 0.01,
    "fee_per_side": 0.0004,
    "summary_path": "results_json_only_timeout18_time_reduce_v36_rr_core_exploration/rrcore_timeout40/summary.json",
    "delta_final_return_pct": 43.85349378972796,
    "delta_pf": -0.0050569269069069556,
    "delta_mdd_pct": -0.176061165946372,
    "delta_max_conc": 0.0,
    "return_retention_pct": 103.22686359559555,
    "mdd_improved": false,
    "pf_improved": false,
    "conc_reduced": false,
    "verdict": "fail"
  },
  {
    "experiment_group": "json_only_short_strict",
    "experiment": "rrcore_wick_or_atr_asym_short_s22",
    "strategy": "overextension_reversion_v1_json_only_timeout18_time_reduce_v36_rr_core_exploration_rrcore_wick_or_atr_asym_short_s22",
    "symbols": NaN,
    "trades": 78191.0,
    "final_asset": 1376.2296865160922,
    "final_return_pct": 1276.2296865160922,
    "peak_asset": 1377.092515844901,
    "peak_growth_pct": 1277.092515844901,
    "win_rate_pct": 30.025194715504345,
    "pf": 1.3072958823986218,
    "mdd_pct": -42.33514030752,
    "max_conc": 391.0,
    "position_fraction": 0.01,
    "fee_per_side": 0.0004,
    "summary_path": "results_json_only_timeout18_time_reduce_v36_rr_core_exploration/rrcore_wick_or_atr_asym_short_s22/summary.json",
    "delta_final_return_pct": -82.78325253671642,
    "delta_pf": 0.03112114998598514,
    "delta_mdd_pct": -3.56537352810593,
    "delta_max_conc": 5.0,
    "return_retention_pct": 93.9085751019844,
    "mdd_improved": false,
    "pf_improved": true,
    "conc_reduced": false,
    "verdict": "fail"
  },
  {
    "experiment_group": "json_only_short_strict",
    "experiment": "rrcore_wick_or_atr",
    "strategy": "overextension_reversion_v1_json_only_timeout18_time_reduce_v36_rr_core_exploration_rrcore_wick_or_atr",
    "symbols": NaN,
    "trades": 86653.0,
    "final_asset": 1542.0635511658825,
    "final_return_pct": 1442.0635511658825,
    "peak_asset": 1543.0303502924162,
    "peak_growth_pct": 1443.0303502924162,
    "win_rate_pct": 29.842013548290307,
    "pf": 1.2896762220061357,
    "mdd_pct": -42.390921248582025,
    "max_conc": 391.0,
    "position_fraction": 0.01,
    "fee_per_side": 0.0004,
    "summary_path": "results_json_only_timeout18_time_reduce_v36_rr_core_exploration/rrcore_wick_or_atr/summary.json",
    "delta_final_return_pct": 83.05061211307384,
    "delta_pf": 0.01350148959349906,
    "delta_mdd_pct": -3.621154469167955,
    "delta_max_conc": 5.0,
    "return_retention_pct": 106.1110979687182,
    "mdd_improved": false,
    "pf_improved": true,
    "conc_reduced": false,
    "verdict": "fail"
  },
  {
    "experiment_group": "json_only_short_strict",
    "experiment": "rrcore_no_earlyreduce",
    "strategy": "overextension_reversion_v1_json_only_timeout18_time_reduce_v36_rr_core_exploration_rrcore_no_earlyreduce",
    "symbols": NaN,
    "trades": 86770.0,
    "final_asset": 781.6249382733656,
    "final_return_pct": 681.6249382733656,
    "peak_asset": 812.4816827164373,
    "peak_growth_pct": 712.4816827164374,
    "win_rate_pct": 41.70104874956782,
    "pf": 1.161093797403725,
    "mdd_pct": -51.04571286317692,
    "max_conc": 386.0,
    "position_fraction": 0.01,
    "fee_per_side": 0.0004,
    "summary_path": "results_json_only_timeout18_time_reduce_v36_rr_core_exploration/rrcore_no_earlyreduce/summary.json",
    "delta_final_return_pct": -677.388000779443,
    "delta_pf": -0.1150809350089117,
    "delta_mdd_pct": -12.275946083762847,
    "delta_max_conc": 0.0,
    "return_retention_pct": 50.15588289751221,
    "mdd_improved": false,
    "pf_improved": false,
    "conc_reduced": false,
    "verdict": "fail"
  }
]