{"group_name":"combinations_json_only_timeout18_time_reduce_v2","experiments":[{"name":"tr_b16_r030_baseline","description":"현재 1위 기준선","enabled":true,"overrides":{}},{"name":"tr_t27_b15_r040_reference","description":"timeout27 강한 비교 기준","enabled":true,"overrides":{"risk":{"timeout_bars":27,"time_reduce_bars":15,"time_reduce_to_risk_frac":0.4}}},{"name":"tr_b15_r025","description":"15봉 후 위험 25%","enabled":true,"overrides":{"risk":{"time_reduce_bars":15,"time_reduce_to_risk_frac":0.25}}},{"name":"tr_b15_r030","description":"15봉 후 위험 30%","enabled":true,"overrides":{"risk":{"time_reduce_bars":15}}},{"name":"tr_b15_r035","description":"15봉 후 위험 35%","enabled":true,"overrides":{"risk":{"time_reduce_bars":15,"time_reduce_to_risk_frac":0.35}}},{"name":"tr_b16_r025","description":"16봉 후 위험 25%","enabled":true,"overrides":{"risk":{"time_reduce_to_risk_frac":0.25}}},{"name":"tr_b16_r035","description":"16봉 후 위험 35%","enabled":true,"overrides":{"risk":{"time_reduce_to_risk_frac":0.35}}},{"name":"tr_b17_r025","description":"17봉 후 위험 25%","enabled":true,"overrides":{"risk":{"time_reduce_bars":17,"time_reduce_to_risk_frac":0.25}}},{"name":"tr_b17_r030","description":"17봉 후 위험 30%","enabled":true,"overrides":{"risk":{"time_reduce_bars":17}}},{"name":"tr_b17_r035","description":"17봉 후 위험 35%","enabled":true,"overrides":{"risk":{"time_reduce_bars":17,"time_reduce_to_risk_frac":0.35}}},{"name":"tr_t27_b15_r030","description":"27봉 + 15봉 후 위험 30%","enabled":true,"overrides":{"risk":{"timeout_bars":27,"time_reduce_bars":15,"time_reduce_to_risk_frac":0.3}}},{"name":"tr_t27_b15_r035","description":"27봉 + 15봉 후 위험 35%","enabled":true,"overrides":{"risk":{"timeout_bars":27,"time_reduce_bars":15,"time_reduce_to_risk_frac":0.35}}},{"name":"tr_t27_b16_r030","description":"27봉 + 16봉 후 위험 30%","enabled":true,"overrides":{"risk":{"timeout_bars":27}}},{"name":"tr_t27_b16_r035","description":"27봉 + 16봉 후 위험 35%","enabled":true,"overrides":{"risk":{"timeout_bars":27,"time_reduce_to_risk_frac":0.35}}},{"name":"tr_t27_b17_r030","description":"27봉 + 17봉 후 위험 30%","enabled":true,"overrides":{"risk":{"timeout_bars":27,"time_reduce_bars":17}}},{"name":"tr_t27_b17_r035","description":"27봉 + 17봉 후 위험 35%","enabled":true,"overrides":{"risk":{"timeout_bars":27,"time_reduce_bars":17,"time_reduce_to_risk_frac":0.35}}},{"name":"tr_t27_ff8_b15_r030","description":"27봉 + ff8 + 15봉 후 위험 30%","enabled":true,"overrides":{"risk":{"timeout_bars":27,"fail_fast_bars":8,"fail_fast_min_progress_r":0.35,"time_reduce_bars":15,"time_reduce_to_risk_frac":0.3}}},{"name":"tr_t27_ff8_b16_r030","description":"27봉 + ff8 + 16봉 후 위험 30%","enabled":true,"overrides":{"risk":{"timeout_bars":27,"fail_fast_bars":8,"fail_fast_min_progress_r":0.35}}},{"name":"tr_t27_ff8_b17_r030","description":"27봉 + ff8 + 17봉 후 위험 30%","enabled":true,"overrides":{"risk":{"timeout_bars":27,"fail_fast_bars":8,"fail_fast_min_progress_r":0.35,"time_reduce_bars":17}}},{"name":"tr_b16_r030_long_light","description":"기준선 + 롱 약강화","enabled":true,"overrides":{"quality":{"long_dev":0.029,"long_rsi_max":24,"long_wick_mult":1.25}}},{"name":"tr_t27_b16_r030_long_light","description":"27봉 + 기준선 + 롱 약강화","enabled":true,"overrides":{"quality":{"long_dev":0.029,"long_rsi_max":24,"long_wick_mult":1.25},"risk":{"timeout_bars":27}}},{"name":"tr_b16_r030_short_light","description":"기준선 + 숏 약강화","enabled":true,"overrides":{"quality":{"short_dev":0.034,"short_rsi_min":77,"short_wick_mult":1.4}}},{"name":"tr_t27_b15_r040_long_light","description":"27봉 + 15봉 후 위험 40% + 롱 약강화","enabled":true,"overrides":{"quality":{"long_dev":0.029,"long_rsi_max":24,"long_wick_mult":1.25},"risk":{"timeout_bars":27,"time_reduce_bars":15,"time_reduce_to_risk_frac":0.4}}},{"name":"tr_b16_r030_atr17","description":"기준선 + atr stop 1.7","enabled":true,"overrides":{"risk":{"atr_stop_mult":1.7}}},{"name":"tr_b16_r030_atr19","description":"기준선 + atr stop 1.9","enabled":true,"overrides":{"risk":{"atr_stop_mult":1.9}}},{"name":"tr_t27_b15_r040_atr17","description":"27봉 + 15봉 후 위험 40% + atr1.7","enabled":true,"overrides":{"risk":{"timeout_bars":27,"time_reduce_bars":15,"time_reduce_to_risk_frac":0.4,"atr_stop_mult":1.7}}},{"name":"tr_t27_b15_r040_atr19","description":"27봉 + 15봉 후 위험 40% + atr1.9","enabled":true,"overrides":{"risk":{"timeout_bars":27,"time_reduce_bars":15,"time_reduce_to_risk_frac":0.4,"atr_stop_mult":1.9}}}]}
